nosqldb/__init__.py
nosqldb/config.py
nosqldb/jsonutils.py
nosqldb/nosqldb.py
nosqldb/utilities.py
nosqldb/kvproxy/doc/ondb.thrift
nosqldb/kvproxy/lib/antlr4-runtime.jar
nosqldb/kvproxy/lib/commonutil.jar
nosqldb/kvproxy/lib/guava.jar
nosqldb/kvproxy/lib/jackson-annotations.jar
nosqldb/kvproxy/lib/jackson-core.jar
nosqldb/kvproxy/lib/jackson-databind.jar
nosqldb/kvproxy/lib/kvclient.jar
nosqldb/kvproxy/lib/kvproxy.jar
nosqldb/kvproxy/lib/libthrift-0.12.0.jar
nosqldb/kvproxy/lib/log4j-1.2.17.jar
nosqldb/kvproxy/lib/sklogger.jar
nosqldb/kvproxy/lib/slf4j-api-1.7.12.jar
nosqldb/kvproxy/lib/slf4j-log4j12-1.7.12.jar
nosqldb/oracle/__init__.py
nosqldb/oracle/kv/__init__.py
nosqldb/oracle/kv/proxy/__init__.py
nosqldb/oracle/kv/proxy/gen/ONDB.py
nosqldb/oracle/kv/proxy/gen/__init__.py
nosqldb/oracle/kv/proxy/gen/constants.py
nosqldb/oracle/kv/proxy/gen/ttypes.py
nosqldb-19.5.1.dist-info/DESCRIPTION.rst
nosqldb-19.5.1.dist-info/METADATA
nosqldb-19.5.1.dist-info/RECORD
nosqldb-19.5.1.dist-info/WHEEL
nosqldb-19.5.1.dist-info/metadata.json
nosqldb-19.5.1.dist-info/top_level.txt
